{
	"menu": [
		{
			"link": "calculator.html#animator",
			"name": "Калькулятор",
			"name_for_main": "Аниматоры",
			"sub": [
				{
					"link": "detail-animator.html",
					"name": "Страница аниматора"
				}
			]
		},
		{
			"link": "calculator.html#photographer",
			"name": "Калькулятор",
			"name_for_main": "Фотографы",
			"sub": [
				{
					"link": "detail-photographer.html",
					"name": "Страница фотографа"
				}
			]
		},
		{
			"link": "calculator.html#area",
			"name": "Калькулятор",
			"name_for_main": "Площадки",
			"sub": [
				{
					"link": "detail-area.html",
					"name": "Страница площадки"
				}
			]
		},
		{
			"link": "calculator.html#service",
			"name": "Калькулятор",
			"name_for_main": "Услуги",
			"sub": [
				{
					"link": "detail-service.html",
					"name": "Страница дополнительной услуги"
				}
			]
		},
		{
			"link": "news.html",
			"name": "Новости",
			"sub": [
				{
					"link": "news-detail.html",
					"name": "Названы лучшие актёры 2017 года"
				}
			]
		},
		{
			"link": "stock.html",
			"name": "Акции",
			"sub": [
				{
					"link": "stock-detail.html",
					"name": "Квест для детей в подарок ко дню рождения"
				}
			]
		},
		{
			"link": "personal-animator.html",
			"name": "Личный кабинет аниматора",
			"sub": [
				{
					"link": "profile-animator.html",
					"name": "Изменение личных данных"
				},
				{
					"link": "application.html",
					"name": "Заявки"
				},
				{
					"link": "offers-training.html",
					"name": "Обучение"
				}
			]
		},
		{
			"link": "personal-photographer.html",
			"name": "Личный кабинет фотографа",
			"sub": [
				{
					"link": "profile-photographer.html",
					"name": "Изменение личных данных"
				}
			]
		},
		{
			"link": "personal-area.html",
			"name": "Личный кабинет площадки",
			"sub": [
				{
					"link": "profile-area.html",
					"name": "Изменение личных данных"
				}
			]
		}
	]
}